dial_basic_nodes/__init__.py
dial_basic_nodes/data_augmentation/__init__.py
dial_basic_nodes/data_augmentation/data_augmentation_node.py
dial_basic_nodes/data_augmentation/data_augmentation_node_cells.py
dial_basic_nodes/data_augmentation/data_augmentation_widget.py
dial_basic_nodes/hyperparameters_config/__init__.py
dial_basic_nodes/hyperparameters_config/hyperparameters_config_node.py
dial_basic_nodes/hyperparameters_config/hyperparameters_config_node_cells.py
dial_basic_nodes/hyperparameters_config/hyperparameters_config_widget.py
dial_basic_nodes/hyperparameters_config/hyperparameters_config_widget_gui.py
dial_basic_nodes/layers_editor/__init__.py
dial_basic_nodes/layers_editor/layers_editor_node.py
dial_basic_nodes/layers_editor/layers_editor_node_cells.py
dial_basic_nodes/layers_editor/layers_editor_widget.py
dial_basic_nodes/layers_editor/layers_tree/__init__.py
dial_basic_nodes/layers_editor/layers_tree/abstract_tree_model/__init__.py
dial_basic_nodes/layers_editor/layers_tree/abstract_tree_model/abstract_tree_model.py
dial_basic_nodes/layers_editor/layers_tree/containers.py
dial_basic_nodes/layers_editor/layers_tree/layers_tree_model.py
dial_basic_nodes/layers_editor/layers_tree/layers_tree_view.py
dial_basic_nodes/layers_editor/layers_tree/layers_tree_widget.py
dial_basic_nodes/layers_editor/model_table/__init__.py
dial_basic_nodes/layers_editor/model_table/containers.py
dial_basic_nodes/layers_editor/model_table/model_table_model.py
dial_basic_nodes/layers_editor/model_table/model_table_view.py
dial_basic_nodes/layers_editor/model_table/model_table_widget.py
dial_basic_nodes/model_checkpoint/__init__.py
dial_basic_nodes/model_checkpoint/model_checkpoint_node.py
dial_basic_nodes/model_checkpoint/model_checkpoint_node_cells.py
dial_basic_nodes/model_checkpoint/model_checkpoint_widget.py
dial_basic_nodes/predefined_models/__init__.py
dial_basic_nodes/predefined_models/predefined_models_node.py
dial_basic_nodes-0.8a0.dist-info/LICENSE
dial_basic_nodes-0.8a0.dist-info/WHEEL
dial_basic_nodes-0.8a0.dist-info/METADATA
dial_basic_nodes-0.8a0.dist-info/RECORD
