Metadata-Version: 2.1
Name: dial-basic-nodes
Version: 0.8a0
Summary: Basic nodes for the Dial app.
Home-page: https://github.com/dial-app/dial-basic-nodes
License: GPL-3.0-only
Keywords: deep-learning,dial-app
Author: David Afonso
Author-email: davafons@gmail.com
Requires-Python: >=3.6.0,<=3.8.3
Classifier: License :: OSI Approved :: GNU General Public License v3 (GPLv3)
Classifier: Programming Language :: Python :: 3
Classifier: Programming Language :: Python :: 3.6
Classifier: Programming Language :: Python :: 3.7
Classifier: Programming Language :: Python :: 3.8
Requires-Dist: dial-core
Project-URL: Repository, https://github.com/dial-app/dial-basic-nodes
